{
    "solicitacao_posicao": "POSI\u00c7\u00c3O",
    "solicitacao_data": "DATA",
    "solicitacao_numero_oficio": "N\u00ba OF\u00cdCIO",
    "solicitacao_cadastro_tipo_nome": "TIPO",
    "solicitacao_cadastro_nome": "NOME",
    "solicitacao_area_interesse_nome": "\u00c1REA DE INTERESSE",
    "solicitacao_assunto_nome": "ASSUNTO",
    "solicitacao_orgao": "ORG\u00c3O",
    "solicitacao_indicacao_sn": "INDICA\u00c7\u00c3O S/N",
    "solicitacao_indicacao_nome": "INDICA\u00c7\u00c3O",
    "solicitacao_reponsavel_analize_nome": "RESPONS\u00c1VEL",
    "solicitacao_local_nome": "N\u00daCLEO",
    "solicitacao_tipo_recebimento_nome": "TP. RECEBIMENTO",
    "solicitacao_data_atendimento": "DT. ATENDIMENTO",
    "solicitacao_atendente_cadastro_nome": "ATENDENTE",
    "solicitacao_cadastrante_cadastro_nome": "CADASTRANTE",
    "solicitacao_descricao": "DESCRI\u00c7\u00c3O DA SOLICITA\u00c7\u00c3O",
    "solicitacao_descricao_texto": "DESCRI\u00c7\u00c3O DA SOLICITA\u00c7\u00c3O",
    "solicitacao_descricao_delta": "DESCRI\u00c7\u00c3O DA SOLICITA\u00c7\u00c3O",
    "solicitacao_aceita_sn": "ACEITA S/N",
    "solicitacao_aceita_recusada": "OBSERVA\u00c7\u00d5ES",
    "solicitacao_aceita_recusada_delta": "OBSERVA\u00c7\u00d5ES",
    "solicitacao_aceita_recusada_texto": "OBSERVA\u00c7\u00d5ES",
    "solicitacao_carta": "RESPOSTA",
    "solicitacao_carta_delta": "RESPOSTA",
    "solicitacao_carta_texto": "RESPOSTA",
    "cadastro_endereco": "ENDERE\u00c7O",
    "cadastro_endereco_numero": "N\u00ba",
    "cadastro_endereco_complemento": "COMP.",
    "cadastro_bairro": "BAIRRO",
    "cadastro_regiao_nome": "REGI\u00c3O",
    "cadastro_municipio_nome": "MUNIC\u00cdPIO",
    "cadastro_email": "E-MAIL 1",
    "cadastro_email2": "E-MAIL 2",
    "cadastro_telefone": "TELEFONE 1",
    "cadastro_telefone2": "TELEFONE 2",
    "cadastro_celular": "CELULAR 1",
    "cadastro_celular2": "CELULAR 2",
    "cadastro_telcom": "TEL. COMERCIAL",
    "cadastro_fax": "FAX",
    "cadastro_estado_nome": "UF",
    "historico_data": "DATA",
    "historico_andamento": "ANDAMENTO",
    "historico_andamento_delta": "ANDAMENTO",
    "historico_andamento_texto": "ANDAMENTO",
    "processo_status": "POSI\u00c7\u00c3O",
    "processo_numero": "N\u00daMERO",
    "oficio_status": "POSI\u00c7\u00c3O",
    "oficio_numero": "N\u00daMERO",
    "oficio_codigo": "C\u00d3DIGO",
    "oficio_convenio": "CONVENIO",
    "oficio_prioridade_nome": "PRIORIDADE",
    "oficio_data_emissao": "DT. EMISS\u00c3O",
    "oficio_data_recebimento": "DT. RECEBIMENTO",
    "oficio_orgao_solicitado_nome": "ORG\u00c3O SOLICITADO",
    "oficio_data_protocolo": "DT. PROTOCOLO",
    "oficio_protocolo_numero": "N\u00ba PROTOCOLO",
    "oficio_orgao_protocolante_nome": "ORG\u00c3O PROTOCOLANTE",
    "oficio_protocolante_funcionario": "FUNCION\u00c1RIO DO ORG\u00c3O",
    "oficio_prazo": "PRASO",
    "oficio_tipo_andamento_nome": "TP. ANDAMENTO",
    "oficio_tipo_recebimento_nome": "TP. RECEBIMENTO",
    "oficio_data_empenho": "DT EMPENHO",
    "oficio_valor_solicitado": "VL. SOLICITADO",
    "oficio_data_pagamento": "VL. RECEBIDO",
    "oficio_valor_recebido": "DATA",
    "oficio_descricao_acao": "DESCRI\u00c7\u00c3O DO OF\u00cdCIO",
    "oficio_descricao_acao_delta": "DESCRI\u00c7\u00c3O DO OF\u00cdCIO",
    "oficio_descricao_acao_texto": "DESCRI\u00c7\u00c3O DO OF\u00cdCIO"
}